cartographer/__init__.py
cartographer/install.py
cartographer/predict.py
xtal_cartographer-0.1.16.dist-info/LICENSE
xtal_cartographer-0.1.16.dist-info/METADATA
xtal_cartographer-0.1.16.dist-info/WHEEL
xtal_cartographer-0.1.16.dist-info/entry_points.txt
xtal_cartographer-0.1.16.dist-info/top_level.txt
xtal_cartographer-0.1.16.dist-info/RECORD
