Metadata-Version: 2.1
Name: xtal-cartographer
Version: 0.1.16
Summary: Cartographer: A Deep-Learning Network for Interpreting Nucleic Acid Electron Density
Author: Jordan Dialpuri
Author-email: jsd523@york.ac.uk
License-File: LICENSE
Requires-Dist: tensorflow
Requires-Dist: tensorflow-addons
Requires-Dist: gemmi
Requires-Dist: tqdm
